dmarcparser/__init__.py
dmarcparser/collector.py
dmarcparser/exceptions.py
dmarcparser/logger.py
dmarcparser/misc.py
dmarcparser/parser.py
dmarcparser/report.py
dmarcparser-0.1.dist-info/LICENSE
dmarcparser-0.1.dist-info/METADATA
dmarcparser-0.1.dist-info/WHEEL
dmarcparser-0.1.dist-info/top_level.txt
dmarcparser-0.1.dist-info/RECORD
