Metadata-Version: 2.1
Name: dmarcparser
Version: 0.1
Summary: Extract and parse DMARC reports/forensic feedback
Author: Anders Nauman
Project-URL: homepage, https://github.com/andersnauman/dmarc-parser
Classifier: Development Status :: 4 - Beta
Classifier: License :: OSI Approved :: GNU General Public License v3 (GPLv3)
License-File: LICENSE
